{
  "Options": {
    "Policies": {
      "PasswordPolicy": {
        "MinimumLength": 8,
        "RequireUppercase": true,
        "RequireLowercase": true,
        "RequireNumbers": true,
        "RequireSymbols": true,
        "TemporaryPasswordValidityDays": 7
      }
    },
    "LambdaConfig": {
      "endpoint": "http://localhost:9991"
    },
    "TriggerFunctions": {
      "PostAuthentication": "PostAuthentication_Authentication"
    },
    "SchemaAttributes": [
      {
        "Name": "sub",
        "AttributeDataType": "String",
        "DeveloperOnlyAttribute": false,
        "Mutable": false,
        "Required": true,
        "StringAttributeConstraints": {
          "MinLength": "1",
          "MaxLength": "2048"
        }
      },
      {
        "Name": "custom:name",
        "AttributeDataType": "String",
        "DeveloperOnlyAttribute": false,
        "Mutable": true,
        "Required": true,
        "StringAttributeConstraints": {
          "MinLength": "0",
          "MaxLength": "2048"
        }
      },
      {
        "Name": "email",
        "AttributeDataType": "String",
        "DeveloperOnlyAttribute": false,
        "Mutable": true,
        "Required": false,
        "StringAttributeConstraints": {
          "MinLength": "0",
          "MaxLength": "2048"
        }
      },
      {
        "Name": "email_verified",
        "AttributeDataType": "Boolean",
        "DeveloperOnlyAttribute": false,
        "Mutable": true,
        "Required": false
      },
      {
        "Name": "updated_at",
        "AttributeDataType": "Number",
        "DeveloperOnlyAttribute": false,
        "Mutable": true,
        "Required": false,
        "NumberAttributeConstraints": {
          "MinValue": "0"
        }
      },
      {
        "Name": "custom:role",
        "AttributeDataType": "String",
        "DeveloperOnlyAttribute": false,
        "Mutable": true,
        "Required": false,
        "NumberAttributeConstraints": {
          "MinValue": "0"
        },
        "StringAttributeConstraints": {
          "MinLength": "0",
          "MaxLength": "255"
        }
      },
      {
        "Name": "custom:userId",
        "AttributeDataType": "String",
        "DeveloperOnlyAttribute": false,
        "Mutable": true,
        "Required": false,
        "StringAttributeConstraints": {
          "MinLength": "0",
          "MaxLength": "255"
        }
      }
    ],
    "VerificationMessageTemplate": {
      "DefaultEmailOption": "CONFIRM_WITH_CODE"
    },
    "MfaConfiguration": "OFF",
    "EstimatedNumberOfUsers": 0,
    "EmailConfiguration": {
      "EmailSendingAccount": "COGNITO_DEFAULT"
    },
    "AdminCreateUserConfig": {
      "AllowAdminCreateUserOnly": false,
      "UnusedAccountValidityDays": 7
    },
    "UsernameAttributes": [
      "email"
    ],
    "Arn": "arn:aws:cognito-idp:local:local:userpool/local_2pHzece7",
    "CreationDate": "2023-01-24T22:34:48.100Z",
    "Id": "local_2pHzece7",
    "LastModifiedDate": "2023-01-24T22:34:48.100Z",
    "Name": "efcms-local"
  },
  "Users": {
    "admin@example.com": {
      "Username": "admin@example.com",
      "Password": "Testing1234$",
      "Attributes": [
        {
          "Name": "sub",
          "Value": "86c3f87b-350b-477d-92c3-43bd095cb006"
        },
        {
          "Name": "custom:userId",
          "Value": "86c3f87b-350b-477d-92c3-43bd095cb006"
        },
        {
          "Name": "email",
          "Value": "admin@example.com"
        },
        {
          "Name": "email_verified",
          "Value": "True"
        },
        {
          "Name": "custom:role",
          "Value": "admin"
        },
        {
          "Name": "custom:name",
          "Value": "Test Admin"
        }
      ],
      "Enabled": false,
      "UserStatus": "CONFIRMED",
      "UserCreateDate": "2023-01-24T23:54:42.392Z",
      "UserLastModifiedDate": "2023-02-21T18:41:41.466Z",
      "RefreshTokens": []
    },
    "docketclerk@example.com": {
      "Username": "docketclerk@example.com",
      "Password": "Testing1234$",
      "Attributes": [
        {
          "Name": "sub",
          "Value": "1805d1ab-18d0-43ec-bafb-654e83405416"
        },
        {
          "Name": "custom:userId",
          "Value": "1805d1ab-18d0-43ec-bafb-654e83405416"
        },
        {
          "Name": "email",
          "Value": "docketclerk@example.com"
        },
        {
          "Name": "email_verified",
          "Value": "True"
        },
        {
          "Name": "custom:role",
          "Value": "docketclerk"
        },
        {
          "Name": "custom:name",
          "Value": "Test Docketclerk"
        }
      ],
      "Enabled": false,
      "UserStatus": "CONFIRMED",
      "UserCreateDate": "2023-01-24T23:54:42.392Z",
      "UserLastModifiedDate": "2023-02-21T18:41:41.466Z",
      "RefreshTokens": []
    },
    "docketclerk1@example.com": {
      "Username": "docketclerk1@example.com",
      "Password": "Testing1234$",
      "Attributes": [
        {
          "Name": "sub",
          "Value": "2805d1ab-18d0-43ec-bafb-654e83405416"
        },
        {
          "Name": "custom:userId",
          "Value": "2805d1ab-18d0-43ec-bafb-654e83405416"
        },
        {
          "Name": "email",
          "Value": "docketclerk1@example.com"
        },
        {
          "Name": "email_verified",
          "Value": "True"
        },
        {
          "Name": "custom:role",
          "Value": "docketclerk"
        },
        {
          "Name": "custom:name",
          "Value": "Test Docketclerk1"
        }
      ],
      "Enabled": false,
      "UserStatus": "CONFIRMED",
      "UserCreateDate": "2023-01-24T23:54:42.392Z",
      "UserLastModifiedDate": "2023-02-21T18:41:41.466Z",
      "RefreshTokens": [
        "eyJhbGciOiJSUzI1NiIsInR5cCI6IkpXVCJ9.eyJjb2duaXRvOnVzZXJuYW1lIjoiZG9ja2V0Y2xlcmsxQGV4YW1wbGUuY29tIiwiZW1haWwiOiJkb2NrZXRjbGVyazFAZXhhbXBsZS5jb20iLCJpYXQiOjE3MTAzNDA2ODEsImp0aSI6IjcyMGIyYzAyLWY5M2YtNDNmNC04OWU5LTFmODhlZGMwOTg1NSIsImV4cCI6MTcxMDk0NTQ4MSwiaXNzIjoiaHR0cDovL2xvY2FsaG9zdDo5MjI5L2xvY2FsXzJwSHplY2U3In0.KX8DDfpu-ES9HYek1URtxtzZo1dWmEzKJ1GkM0JjCfBRNIsoCRCf91VR7PXJjtc6fBggRx1ZN2CCm5hvJxrA9ptkkCMSSXbsrx9JyG4DOQ_cHbhlRsvo-jTvFLbCC4tPNn_svxPoazw7n2XZoqEfB1bDXO9VF74y4l4VS6bRf0ALJGWYUq34wRSxUxY1qaZ6ubaCn19EM5Vgnw62GwhmvcJUqiULYvuDSxLrymRYxiotgWBtJQus-cdWhVWMLAZF_WXIR0-6K7k9JkeRjqRxTH-KkecYXvJUmkVysjs1Ra4DO8PZ70swKKHf4eIrZodsat-i0f3bDPuK_TrycrMAnA"
      ]
    },
    "caseservicessupervisor@example.com": {
      "Username": "caseservicessupervisor@example.com",
      "Password": "Testing1234$",
      "Attributes": [
        {
          "Name": "sub",
          "Value": "35959d1a-0981-40b2-a93d-f65c7977db52"
        },
        {
          "Name": "custom:userId",
          "Value": "35959d1a-0981-40b2-a93d-f65c7977db52"
        },
        {
          "Name": "email",
          "Value": "caseservicessupervisor@example.com"
        },
        {
          "Name": "email_verified",
          "Value": "True"
        },
        {
          "Name": "custom:role",
          "Value": "caseServicesSupervisor"
        },
        {
          "Name": "custom:name",
          "Value": "Test Case Services Supervisor"
        }
      ],
      "Enabled": false,
      "UserStatus": "CONFIRMED",
      "UserCreateDate": "2023-01-24T23:54:42.392Z",
      "UserLastModifiedDate": "2023-02-21T18:41:41.466Z",
      "RefreshTokens": []
    },
    "judgefieri@example.com": {
      "Username": "judgefieri@example.com",
      "Password": "Testing1234$",
      "Attributes": [
        {
          "Name": "sub",
          "Value": "dadbad42-18d0-43ec-bafb-654e83405416"
        },
        {
          "Name": "custom:userId",
          "Value": "dadbad42-18d0-43ec-bafb-654e83405416"
        },
        {
          "Name": "email",
          "Value": "judgefieri@example.com"
        },
        {
          "Name": "email_verified",
          "Value": "True"
        },
        {
          "Name": "custom:role",
          "Value": "legacyJudge"
        },
        {
          "Name": "custom:name",
          "Value": "Fieri"
        }
      ],
      "Enabled": false,
      "UserStatus": "CONFIRMED",
      "UserCreateDate": "2023-01-24T23:54:42.392Z",
      "UserLastModifiedDate": "2023-02-21T18:41:41.466Z",
      "RefreshTokens": []
    },
    "judgecolvin@example.com": {
      "Username": "judgecolvin@example.com",
      "Password": "Testing1234$",
      "Attributes": [
        {
          "Name": "sub",
          "Value": "dabbad00-18d0-43ec-bafb-654e83405416"
        },
        {
          "Name": "custom:userId",
          "Value": "dabbad00-18d0-43ec-bafb-654e83405416"
        },
        {
          "Name": "email",
          "Value": "judgecolvin@example.com"
        },
        {
          "Name": "email_verified",
          "Value": "True"
        },
        {
          "Name": "custom:role",
          "Value": "judge"
        },
        {
          "Name": "custom:name",
          "Value": "Colvin"
        }
      ],
      "Enabled": false,
      "UserStatus": "CONFIRMED",
      "UserCreateDate": "2023-01-24T23:54:42.392Z",
      "UserLastModifiedDate": "2023-02-21T18:41:41.466Z",
      "RefreshTokens": []
    },
    "judgemowry@example.com": {
      "Username": "judgemowry@example.com",
      "Password": "Testing1234$",
      "Attributes": [
        {
          "Name": "sub",
          "Value": "09b7c6c9-2d9e-43a5-83a4-096ae5362725"
        },
        {
          "Name": "custom:userId",
          "Value": "09b7c6c9-2d9e-43a5-83a4-096ae5362725"
        },
        {
          "Name": "email",
          "Value": "judgemowry@example.com"
        },
        {
          "Name": "email_verified",
          "Value": "True"
        },
        {
          "Name": "custom:role",
          "Value": "judge"
        },
        {
          "Name": "custom:name",
          "Value": "Mowry"
        }
      ],
      "Enabled": false,
      "UserStatus": "CONFIRMED",
      "UserCreateDate": "2023-01-24T23:54:42.392Z",
      "UserLastModifiedDate": "2023-02-21T18:41:41.466Z",
      "RefreshTokens": []
    },
    "judgeashford@example.com": {
      "Username": "judgeashford@example.com",
      "Password": "Testing1234$",
      "Attributes": [
        {
          "Name": "sub",
          "Value": "dabbad01-18d0-43ec-bafb-654e83405416"
        },
        {
          "Name": "custom:userId",
          "Value": "dabbad01-18d0-43ec-bafb-654e83405416"
        },
        {
          "Name": "email",
          "Value": "judgeashford@example.com"
        },
        {
          "Name": "email_verified",
          "Value": "True"
        },
        {
          "Name": "custom:role",
          "Value": "judge"
        },
        {
          "Name": "custom:name",
          "Value": "Ashford"
        }
      ],
      "Enabled": false,
      "UserStatus": "CONFIRMED",
      "UserCreateDate": "2023-01-24T23:54:42.392Z",
      "UserLastModifiedDate": "2023-02-21T18:41:41.466Z",
      "RefreshTokens": []
    },
    "judgefoley@example.com": {
      "Username": "judgefoley@example.com",
      "Password": "Testing1234$",
      "Attributes": [
        {
          "Name": "sub",
          "Value": "659789b4-acc5-40b7-9318-3354e7eb8604"
        },
        {
          "Name": "custom:userId",
          "Value": "659789b4-acc5-40b7-9318-3354e7eb8604"
        },
        {
          "Name": "email",
          "Value": "judgefoley@example.com"
        },
        {
          "Name": "email_verified",
          "Value": "True"
        },
        {
          "Name": "custom:role",
          "Value": "judge"
        },
        {
          "Name": "custom:name",
          "Value": "Foley"
        }
      ],
      "Enabled": false,
      "UserStatus": "CONFIRMED",
      "UserCreateDate": "2023-01-24T23:54:42.392Z",
      "UserLastModifiedDate": "2023-02-21T18:41:41.466Z",
      "RefreshTokens": []
    },
    "judgebuch@example.com": {
      "Username": "judgebuch@example.com",
      "Password": "Testing1234$",
      "Attributes": [
        {
          "Name": "sub",
          "Value": "dabbad02-18d0-43ec-bafb-654e83405416"
        },
        {
          "Name": "custom:userId",
          "Value": "dabbad02-18d0-43ec-bafb-654e83405416"
        },
        {
          "Name": "email",
          "Value": "judgebuch@example.com"
        },
        {
          "Name": "email_verified",
          "Value": "True"
        },
        {
          "Name": "custom:role",
          "Value": "judge"
        },
        {
          "Name": "custom:name",
          "Value": "Buch"
        }
      ],
      "Enabled": false,
      "UserStatus": "CONFIRMED",
      "UserCreateDate": "2023-01-24T23:54:42.392Z",
      "UserLastModifiedDate": "2023-02-21T18:41:41.466Z",
      "RefreshTokens": []
    },
    "judgecarluzzo@example.com": {
      "Username": "judgecarluzzo@example.com",
      "Password": "Testing1234$",
      "Attributes": [
        {
          "Name": "sub",
          "Value": "dabbad03-18d0-43ec-bafb-654e83405416"
        },
        {
          "Name": "custom:userId",
          "Value": "dabbad03-18d0-43ec-bafb-654e83405416"
        },
        {
          "Name": "email",
          "Value": "judgecarluzzo@example.com"
        },
        {
          "Name": "email_verified",
          "Value": "True"
        },
        {
          "Name": "custom:role",
          "Value": "judge"
        },
        {
          "Name": "custom:name",
          "Value": "Carluzzo"
        }
      ],
      "Enabled": false,
      "UserStatus": "CONFIRMED",
      "UserCreateDate": "2023-01-24T23:54:42.392Z",
      "UserLastModifiedDate": "2023-02-21T18:41:41.466Z",
      "RefreshTokens": []
    },
    "judgecohen@example.com": {
      "Username": "judgecohen@example.com",
      "Password": "Testing1234$",
      "Attributes": [
        {
          "Name": "sub",
          "Value": "dabbad04-18d0-43ec-bafb-654e83405416"
        },
        {
          "Name": "custom:userId",
          "Value": "dabbad04-18d0-43ec-bafb-654e83405416"
        },
        {
          "Name": "email",
          "Value": "judgecohen@example.com"
        },
        {
          "Name": "email_verified",
          "Value": "True"
        },
        {
          "Name": "custom:role",
          "Value": "judge"
        },
        {
          "Name": "custom:name",
          "Value": "Cohen"
        }
      ],
      "Enabled": false,
      "UserStatus": "CONFIRMED",
      "UserCreateDate": "2023-01-24T23:54:42.392Z",
      "UserLastModifiedDate": "2023-02-21T18:41:41.466Z",
      "RefreshTokens": []
    },
    "judgegustafson@example.com": {
      "Username": "judgegustafson@example.com",
      "Password": "Testing1234$",
      "Attributes": [
        {
          "Name": "sub",
          "Value": "dabbad05-18d0-43ec-bafb-654e83405416"
        },
        {
          "Name": "custom:userId",
          "Value": "dabbad05-18d0-43ec-bafb-654e83405416"
        },
        {
          "Name": "email",
          "Value": "judgegustafson@example.com"
        },
        {
          "Name": "email_verified",
          "Value": "True"
        },
        {
          "Name": "custom:role",
          "Value": "judge"
        },
        {
          "Name": "custom:name",
          "Value": "Gustafson"
        }
      ],
      "Enabled": false,
      "UserStatus": "CONFIRMED",
      "UserCreateDate": "2023-01-24T23:54:42.392Z",
      "UserLastModifiedDate": "2023-02-21T18:41:41.466Z",
      "RefreshTokens": []
    },
    "judgepugh@example.com": {
      "Username": "judgepugh@example.com",
      "Password": "Testing1234$",
      "Attributes": [
        {
          "Name": "sub",
          "Value": "dabbad06-18d0-43ec-bafb-654e83405416"
        },
        {
          "Name": "custom:userId",
          "Value": "dabbad06-18d0-43ec-bafb-654e83405416"
        },
        {
          "Name": "email",
          "Value": "judgepugh@example.com"
        },
        {
          "Name": "email_verified",
          "Value": "True"
        },
        {
          "Name": "custom:role",
          "Value": "judge"
        },
        {
          "Name": "custom:name",
          "Value": "Pugh"
        }
      ],
      "Enabled": false,
      "UserStatus": "CONFIRMED",
      "UserCreateDate": "2023-01-24T23:54:42.392Z",
      "UserLastModifiedDate": "2023-02-21T18:41:41.466Z",
      "RefreshTokens": []
    },
    "judgeurda@example.com": {
      "Username": "judgeurda@example.com",
      "Password": "Testing1234$",
      "Attributes": [
        {
          "Name": "sub",
          "Value": "dabbad0a-18d0-43ec-bafb-654e83405416"
        },
        {
          "Name": "custom:userId",
          "Value": "dabbad0a-18d0-43ec-bafb-654e83405416"
        },
        {
          "Name": "email",
          "Value": "judgeurda@example.com"
        },
        {
          "Name": "email_verified",
          "Value": "True"
        },
        {
          "Name": "custom:role",
          "Value": "judge"
        },
        {
          "Name": "custom:name",
          "Value": "Urda"
        }
      ],
      "Enabled": false,
      "UserStatus": "CONFIRMED",
      "UserCreateDate": "2023-01-24T23:54:42.392Z",
      "UserLastModifiedDate": "2023-02-21T18:41:41.466Z",
      "RefreshTokens": []
    },
    "adc@example.com": {
      "Username": "adc@example.com",
      "Password": "Testing1234$",
      "Attributes": [
        {
          "Name": "sub",
          "Value": "6805d1ab-18d0-43ec-bafb-654e83405416"
        },
        {
          "Name": "custom:userId",
          "Value": "6805d1ab-18d0-43ec-bafb-654e83405416"
        },
        {
          "Name": "email",
          "Value": "adc@example.com"
        },
        {
          "Name": "email_verified",
          "Value": "True"
        },
        {
          "Name": "custom:role",
          "Value": "adc"
        },
        {
          "Name": "custom:name",
          "Value": "Test ADC"
        }
      ],
      "Enabled": false,
      "UserStatus": "CONFIRMED",
      "UserCreateDate": "2023-01-24T23:54:42.392Z",
      "UserLastModifiedDate": "2023-02-21T18:41:41.466Z",
      "RefreshTokens": []
    },
    "petitionsclerk@example.com": {
      "Username": "petitionsclerk@example.com",
      "Password": "Testing1234$",
      "Attributes": [
        {
          "Name": "sub",
          "Value": "3805d1ab-18d0-43ec-bafb-654e83405416"
        },
        {
          "Name": "custom:userId",
          "Value": "3805d1ab-18d0-43ec-bafb-654e83405416"
        },
        {
          "Name": "email",
          "Value": "petitionsclerk@example.com"
        },
        {
          "Name": "email_verified",
          "Value": "True"
        },
        {
          "Name": "custom:role",
          "Value": "petitionsclerk"
        },
        {
          "Name": "custom:name",
          "Value": "Test Petitionsclerk"
        }
      ],
      "Enabled": false,
      "UserStatus": "CONFIRMED",
      "UserCreateDate": "2023-01-24T23:54:42.392Z",
      "UserLastModifiedDate": "2023-02-21T18:41:41.466Z",
      "RefreshTokens": []
    },
    "petitionsclerk1@example.com": {
      "Username": "petitionsclerk1@example.com",
      "Password": "Testing1234$",
      "Attributes": [
        {
          "Name": "sub",
          "Value": "4805d1ab-18d0-43ec-bafb-654e83405416"
        },
        {
          "Name": "custom:userId",
          "Value": "4805d1ab-18d0-43ec-bafb-654e83405416"
        },
        {
          "Name": "email",
          "Value": "petitionsclerk1@example.com"
        },
        {
          "Name": "email_verified",
          "Value": "True"
        },
        {
          "Name": "custom:role",
          "Value": "petitionsclerk"
        },
        {
          "Name": "custom:name",
          "Value": "Test Petitionsclerk1"
        }
      ],
      "Enabled": false,
      "UserStatus": "CONFIRMED",
      "UserCreateDate": "2023-01-24T23:54:42.392Z",
      "UserLastModifiedDate": "2023-02-21T18:41:41.466Z",
      "RefreshTokens": []
    },
    "privatePractitioner@example.com": {
      "Username": "privatePractitioner@example.com",
      "Password": "Testing1234$",
      "Attributes": [
        {
          "Name": "sub",
          "Value": "9805d1ab-18d0-43ec-bafb-654e83405416"
        },
        {
          "Name": "custom:userId",
          "Value": "9805d1ab-18d0-43ec-bafb-654e83405416"
        },
        {
          "Name": "email",
          "Value": "privatePractitioner@example.com"
        },
        {
          "Name": "email_verified",
          "Value": "True"
        },
        {
          "Name": "custom:role",
          "Value": "privatePractitioner"
        },
        {
          "Name": "custom:name",
          "Value": "Test Private Practitioner"
        }
      ],
      "Enabled": false,
      "UserStatus": "CONFIRMED",
      "UserCreateDate": "2023-01-24T23:54:42.392Z",
      "UserLastModifiedDate": "2023-02-21T18:41:41.466Z",
      "RefreshTokens": []
    },
    "privatePractitioner1@example.com": {
      "Username": "privatePractitioner1@example.com",
      "Password": "Testing1234$",
      "Attributes": [
        {
          "Name": "sub",
          "Value": "ad07b846-8933-4778-9fe2-b5d8ac8ad728"
        },
        {
          "Name": "custom:userId",
          "Value": "ad07b846-8933-4778-9fe2-b5d8ac8ad728"
        },
        {
          "Name": "email",
          "Value": "privatePractitioner1@example.com"
        },
        {
          "Name": "email_verified",
          "Value": "True"
        },
        {
          "Name": "custom:role",
          "Value": "privatePractitioner"
        },
        {
          "Name": "custom:name",
          "Value": "Test Private Practitioner"
        }
      ],
      "Enabled": false,
      "UserStatus": "CONFIRMED",
      "UserCreateDate": "2023-01-24T23:54:42.392Z",
      "UserLastModifiedDate": "2023-02-21T18:41:41.466Z",
      "RefreshTokens": []
    },
    "privatePractitioner2@example.com": {
      "Username": "privatePractitioner2@example.com",
      "Password": "Testing1234$",
      "Attributes": [
        {
          "Name": "sub",
          "Value": "8e4959cd-3e13-4bf6-95bf-a276cc63b9e1"
        },
        {
          "Name": "custom:userId",
          "Value": "8e4959cd-3e13-4bf6-95bf-a276cc63b9e1"
        },
        {
          "Name": "email",
          "Value": "privatePractitioner2@example.com"
        },
        {
          "Name": "email_verified",
          "Value": "True"
        },
        {
          "Name": "custom:role",
          "Value": "privatePractitioner"
        },
        {
          "Name": "custom:name",
          "Value": "Lilah Gilbert"
        }
      ],
      "Enabled": false,
      "UserStatus": "CONFIRMED",
      "UserCreateDate": "2023-01-24T23:54:42.392Z",
      "UserLastModifiedDate": "2023-02-21T18:41:41.466Z",
      "RefreshTokens": []
    },
    "privatePractitioner3@example.com": {
      "Username": "privatePractitioner3@example.com",
      "Password": "Testing1234$",
      "Attributes": [
        {
          "Name": "sub",
          "Value": "9f25dc2c-764a-435c-86dd-323e53634537"
        },
        {
          "Name": "custom:userId",
          "Value": "9f25dc2c-764a-435c-86dd-323e53634537"
        },
        {
          "Name": "email",
          "Value": "privatePractitioner3@example.com"
        },
        {
          "Name": "email_verified",
          "Value": "True"
        },
        {
          "Name": "custom:role",
          "Value": "privatePractitioner"
        },
        {
          "Name": "custom:name",
          "Value": "Clark Stark"
        }
      ],
      "Enabled": false,
      "UserStatus": "CONFIRMED",
      "UserCreateDate": "2023-01-24T23:54:42.392Z",
      "UserLastModifiedDate": "2023-02-21T18:41:41.466Z",
      "RefreshTokens": []
    },
    "privatePractitioner4@example.com": {
      "Username": "privatePractitioner4@example.com",
      "Password": "Testing1234$",
      "Attributes": [
        {
          "Name": "sub",
          "Value": "29e9b4d1-63bc-4f66-b230-59a3a9ae44eb"
        },
        {
          "Name": "custom:userId",
          "Value": "29e9b4d1-63bc-4f66-b230-59a3a9ae44eb"
        },
        {
          "Name": "email",
          "Value": "privatePractitioner4@example.com"
        },
        {
          "Name": "email_verified",
          "Value": "True"
        },
        {
          "Name": "custom:role",
          "Value": "privatePractitioner"
        },
        {
          "Name": "custom:name",
          "Value": "Alden Rivas"
        }
      ],
      "Enabled": false,
      "UserStatus": "CONFIRMED",
      "UserCreateDate": "2023-01-24T23:54:42.392Z",
      "UserLastModifiedDate": "2023-02-21T18:41:41.466Z",
      "RefreshTokens": []
    },
    "privatePractitioner99@example.com": {
      "Username": "privatePractitioner99@example.com",
      "Password": "Testing1234$",
      "Attributes": [
        {
          "Name": "sub",
          "Value": "a6318a31-8aa4-4002-a7b0-1192af19dbb9"
        },
        {
          "Name": "custom:userId",
          "Value": "a6318a31-8aa4-4002-a7b0-1192af19dbb9"
        },
        {
          "Name": "email",
          "Value": "privatePractitioner99@example.com"
        },
        {
          "Name": "email_verified",
          "Value": "True"
        },
        {
          "Name": "custom:role",
          "Value": "privatePractitioner"
        },
        {
          "Name": "custom:name",
          "Value": "Test Private Practitioner 99"
        }
      ],
      "Enabled": false,
      "UserStatus": "CONFIRMED",
      "UserCreateDate": "2023-01-24T23:54:42.392Z",
      "UserLastModifiedDate": "2023-02-21T18:41:41.466Z",
      "RefreshTokens": []
    },
    "irspractitioner@example.com": {
      "Username": "irspractitioner@example.com",
      "Password": "Testing1234$",
      "Attributes": [
        {
          "Name": "sub",
          "Value": "5805d1ab-18d0-43ec-bafb-654e83405416"
        },
        {
          "Name": "custom:userId",
          "Value": "5805d1ab-18d0-43ec-bafb-654e83405416"
        },
        {
          "Name": "email",
          "Value": "irspractitioner@example.com"
        },
        {
          "Name": "email_verified",
          "Value": "True"
        },
        {
          "Name": "custom:role",
          "Value": "irsPractitioner"
        },
        {
          "Name": "custom:name",
          "Value": "Test IRS Practitioner"
        }
      ],
      "Enabled": false,
      "UserStatus": "CONFIRMED",
      "UserCreateDate": "2023-01-24T23:54:42.392Z",
      "UserLastModifiedDate": "2023-02-21T18:41:41.466Z",
      "RefreshTokens": []
    },
    "irspractitioner1@example.com": {
      "Username": "irspractitioner1@example.com",
      "Password": "Testing1234$",
      "Attributes": [
        {
          "Name": "sub",
          "Value": "5fb6e815-b5d3-459b-b08b-49c61f0fce5e"
        },
        {
          "Name": "custom:userId",
          "Value": "5fb6e815-b5d3-459b-b08b-49c61f0fce5e"
        },
        {
          "Name": "email",
          "Value": "irspractitioner1@example.com"
        },
        {
          "Name": "email_verified",
          "Value": "True"
        },
        {
          "Name": "custom:role",
          "Value": "irsPractitioner"
        },
        {
          "Name": "custom:name",
          "Value": "Test IRS Practitioner1"
        }
      ],
      "Enabled": false,
      "UserStatus": "CONFIRMED",
      "UserCreateDate": "2023-01-24T23:54:42.392Z",
      "UserLastModifiedDate": "2023-02-21T18:41:41.466Z",
      "RefreshTokens": []
    },
    "irspractitioner2@example.com": {
      "Username": "irspractitioner2@example.com",
      "Password": "Testing1234$",
      "Attributes": [
        {
          "Name": "sub",
          "Value": "2d9a7229-7d5a-459f-84ad-754504a9f10f"
        },
        {
          "Name": "custom:userId",
          "Value": "2d9a7229-7d5a-459f-84ad-754504a9f10f"
        },
        {
          "Name": "email",
          "Value": "irspractitioner2@example.com"
        },
        {
          "Name": "email_verified",
          "Value": "True"
        },
        {
          "Name": "custom:role",
          "Value": "irsPractitioner"
        },
        {
          "Name": "custom:name",
          "Value": "Nero West"
        }
      ],
      "Enabled": false,
      "UserStatus": "CONFIRMED",
      "UserCreateDate": "2023-01-24T23:54:42.392Z",
      "UserLastModifiedDate": "2023-02-21T18:41:41.466Z",
      "RefreshTokens": []
    },
    "irspractitioner3@example.com": {
      "Username": "irspractitioner3@example.com",
      "Password": "Testing1234$",
      "Attributes": [
        {
          "Name": "sub",
          "Value": "5c43a30d-9c3d-41be-ad13-3b6d7cef54fc"
        },
        {
          "Name": "custom:userId",
          "Value": "5c43a30d-9c3d-41be-ad13-3b6d7cef54fc"
        },
        {
          "Name": "email",
          "Value": "irspractitioner3@example.com"
        },
        {
          "Name": "email_verified",
          "Value": "True"
        },
        {
          "Name": "custom:role",
          "Value": "irsPractitioner"
        },
        {
          "Name": "custom:name",
          "Value": "Stuart Morrison"
        }
      ],
      "Enabled": false,
      "UserStatus": "CONFIRMED",
      "UserCreateDate": "2023-01-24T23:54:42.392Z",
      "UserLastModifiedDate": "2023-02-21T18:41:41.466Z",
      "RefreshTokens": []
    },
    "irspractitioner4@example.com": {
      "Username": "irspractitioner4@example.com",
      "Password": "Testing1234$",
      "Attributes": [
        {
          "Name": "sub",
          "Value": "726c38b1-1432-49b3-9383-77a998c0ba4f"
        },
        {
          "Name": "custom:userId",
          "Value": "726c38b1-1432-49b3-9383-77a998c0ba4f"
        },
        {
          "Name": "email",
          "Value": "irspractitioner4@example.com"
        },
        {
          "Name": "email_verified",
          "Value": "True"
        },
        {
          "Name": "custom:role",
          "Value": "irsPractitioner"
        },
        {
          "Name": "custom:name",
          "Value": "Jaquelyn Lane"
        }
      ],
      "Enabled": false,
      "UserStatus": "CONFIRMED",
      "UserCreateDate": "2023-01-24T23:54:42.392Z",
      "UserLastModifiedDate": "2023-02-21T18:41:41.466Z",
      "RefreshTokens": []
    },
    "petitioner@example.com": {
      "Username": "petitioner@example.com",
      "Password": "Testing1234$",
      "Attributes": [
        {
          "Name": "sub",
          "Value": "7805d1ab-18d0-43ec-bafb-654e83405416"
        },
        {
          "Name": "custom:userId",
          "Value": "7805d1ab-18d0-43ec-bafb-654e83405416"
        },
        {
          "Name": "email",
          "Value": "petitioner@example.com"
        },
        {
          "Name": "email_verified",
          "Value": "True"
        },
        {
          "Name": "custom:role",
          "Value": "petitioner"
        },
        {
          "Name": "custom:name",
          "Value": "Test Petitioner"
        }
      ],
      "Enabled": false,
      "UserStatus": "CONFIRMED",
      "UserCreateDate": "2023-01-24T23:54:42.392Z",
      "UserLastModifiedDate": "2023-02-21T18:41:41.466Z",
      "RefreshTokens": []
    },
    "petitioner1@example.com": {
      "Username": "petitioner1@example.com",
      "Password": "Testing1234$",
      "Attributes": [
        {
          "Name": "sub",
          "Value": "b84acb19-008f-4911-bfb6-773ca4020464"
        },
        {
          "Name": "custom:userId",
          "Value": "b84acb19-008f-4911-bfb6-773ca4020464"
        },
        {
          "Name": "email",
          "Value": "petitioner1@example.com"
        },
        {
          "Name": "email_verified",
          "Value": "True"
        },
        {
          "Name": "custom:role",
          "Value": "petitioner"
        },
        {
          "Name": "custom:name",
          "Value": "Test Petitioner 1"
        }
      ],
      "Enabled": false,
      "UserStatus": "CONFIRMED",
      "UserCreateDate": "2023-01-24T23:54:42.392Z",
      "UserLastModifiedDate": "2023-02-21T18:41:41.466Z",
      "RefreshTokens": []
    },
    "petitioner2@example.com": {
      "Username": "petitioner2@example.com",
      "Password": "Testing1234$",
      "Attributes": [
        {
          "Name": "sub",
          "Value": "7805d1ab-18d0-43ec-bafb-654e83405417"
        },
        {
          "Name": "custom:userId",
          "Value": "7805d1ab-18d0-43ec-bafb-654e83405417"
        },
        {
          "Name": "email",
          "Value": "petitioner2@example.com"
        },
        {
          "Name": "email_verified",
          "Value": "True"
        },
        {
          "Name": "custom:role",
          "Value": "petitioner"
        },
        {
          "Name": "custom:name",
          "Value": "Test Petitioner 2"
        }
      ],
      "Enabled": false,
      "UserStatus": "CONFIRMED",
      "UserCreateDate": "2023-01-24T23:54:42.392Z",
      "UserLastModifiedDate": "2023-02-21T18:41:41.466Z",
      "RefreshTokens": []
    },
    "petitioner3@example.com": {
      "Username": "petitioner3@example.com",
      "Password": "Testing1234$",
      "Attributes": [
        {
          "Name": "sub",
          "Value": "7805d1ab-18d0-43ec-bafb-654e83405418"
        },
        {
          "Name": "custom:userId",
          "Value": "7805d1ab-18d0-43ec-bafb-654e83405418"
        },
        {
          "Name": "email",
          "Value": "petitioner3@example.com"
        },
        {
          "Name": "email_verified",
          "Value": "True"
        },
        {
          "Name": "custom:role",
          "Value": "petitioner"
        },
        {
          "Name": "custom:name",
          "Value": "Test Petitioner 3"
        }
      ],
      "Enabled": false,
      "UserStatus": "CONFIRMED",
      "UserCreateDate": "2023-01-24T23:54:42.392Z",
      "UserLastModifiedDate": "2023-02-21T18:41:41.466Z",
      "RefreshTokens": []
    },
    "petitioner4@example.com": {
      "Username": "petitioner4@example.com",
      "Password": "Testing1234$",
      "Attributes": [
        {
          "Name": "sub",
          "Value": "b3e1941f-230a-47bb-80ec-6b561c1765cd"
        },
        {
          "Name": "custom:userId",
          "Value": "b3e1941f-230a-47bb-80ec-6b561c1765cd"
        },
        {
          "Name": "email",
          "Value": "petitioner4@example.com"
        },
        {
          "Name": "email_verified",
          "Value": "True"
        },
        {
          "Name": "custom:role",
          "Value": "petitioner"
        },
        {
          "Name": "custom:name",
          "Value": "Test Petitioner 4"
        }
      ],
      "Enabled": false,
      "UserStatus": "CONFIRMED",
      "UserCreateDate": "2023-01-24T23:54:42.392Z",
      "UserLastModifiedDate": "2023-02-21T18:41:41.466Z",
      "RefreshTokens": []
    },
    "petitioner7@example.com": {
      "Username": "petitioner7@example.com",
      "Password": "Testing1234$",
      "Attributes": [
        {
          "Name": "sub",
          "Value": "d3e1941f-230a-47bb-80ec-6b561c1765cd"
        },
        {
          "Name": "custom:userId",
          "Value": "d3e1941f-230a-47bb-80ec-6b561c1765cd"
        },
        {
          "Name": "email",
          "Value": "petitioner7@example.com"
        },
        {
          "Name": "email_verified",
          "Value": "True"
        },
        {
          "Name": "custom:role",
          "Value": "petitioner"
        },
        {
          "Name": "custom:name",
          "Value": "Test Petitioner 7"
        }
      ],
      "Enabled": false,
      "UserStatus": "CONFIRMED",
      "UserCreateDate": "2023-01-24T23:54:42.392Z",
      "UserLastModifiedDate": "2023-02-21T18:41:41.466Z",
      "RefreshTokens": []
    },
    "petitioner8@example.com": {
      "Username": "petitioner8@example.com",
      "Password": "Testing1234$",
      "Attributes": [
        {
          "Name": "sub",
          "Value": "e3e1941f-230a-47bb-80ec-6b561c1765cd"
        },
        {
          "Name": "custom:userId",
          "Value": "e3e1941f-230a-47bb-80ec-6b561c1765cd"
        },
        {
          "Name": "email",
          "Value": "petitioner8@example.com"
        },
        {
          "Name": "email_verified",
          "Value": "True"
        },
        {
          "Name": "custom:role",
          "Value": "petitioner"
        },
        {
          "Name": "custom:name",
          "Value": "Test Petitioner 8"
        }
      ],
      "Enabled": false,
      "UserStatus": "CONFIRMED",
      "UserCreateDate": "2023-01-24T23:54:42.392Z",
      "UserLastModifiedDate": "2023-02-21T18:41:41.466Z",
      "RefreshTokens": []
    },
    "petitioner9@example.com": {
      "Username": "petitioner9@example.com",
      "Password": "Testing1234$",
      "Attributes": [
        {
          "Name": "sub",
          "Value": "b2d1941f-230a-47bb-80ec-6b561c1765cd"
        },
        {
          "Name": "custom:userId",
          "Value": "b2d1941f-230a-47bb-80ec-6b561c1765cd"
        },
        {
          "Name": "email",
          "Value": "petitioner9@example.com"
        },
        {
          "Name": "email_verified",
          "Value": "True"
        },
        {
          "Name": "custom:role",
          "Value": "petitioner"
        },
        {
          "Name": "custom:name",
          "Value": "Test Petitioner 9"
        }
      ],
      "Enabled": false,
      "UserStatus": "CONFIRMED",
      "UserCreateDate": "2023-01-24T23:54:42.392Z",
      "UserLastModifiedDate": "2023-02-21T18:41:41.466Z",
      "RefreshTokens": []
    },
    "admissionsclerk@example.com": {
      "Username": "admissionsclerk@example.com",
      "Password": "Testing1234$",
      "Attributes": [
        {
          "Name": "sub",
          "Value": "9d7d63b7-d7a5-4905-ba89-ef71bf30057f"
        },
        {
          "Name": "custom:userId",
          "Value": "9d7d63b7-d7a5-4905-ba89-ef71bf30057f"
        },
        {
          "Name": "email",
          "Value": "admissionsclerk@example.com"
        },
        {
          "Name": "email_verified",
          "Value": "True"
        },
        {
          "Name": "custom:role",
          "Value": "admissionsclerk"
        },
        {
          "Name": "custom:name",
          "Value": "Test Admissions Clerk"
        }
      ],
      "Enabled": false,
      "UserStatus": "CONFIRMED",
      "UserCreateDate": "2023-01-24T23:54:42.392Z",
      "UserLastModifiedDate": "2023-02-21T18:41:41.466Z",
      "RefreshTokens": []
    },
    "admissionsclerk1@example.com": {
      "Username": "admissionsclerk1@example.com",
      "Password": "Testing1234$",
      "Attributes": [
        {
          "Name": "sub",
          "Value": "9d7d63a3-d7a5-4905-ba89-ef71bf30057f"
        },
        {
          "Name": "custom:userId",
          "Value": "9d7d63a3-d7a5-4905-ba89-ef71bf30057f"
        },
        {
          "Name": "email",
          "Value": "admissionsclerk1@example.com"
        },
        {
          "Name": "email_verified",
          "Value": "True"
        },
        {
          "Name": "custom:role",
          "Value": "admissionsclerk"
        },
        {
          "Name": "custom:name",
          "Value": "Test Admissions Clerk1"
        }
      ],
      "Enabled": false,
      "UserStatus": "CONFIRMED",
      "UserCreateDate": "2023-01-24T23:54:42.392Z",
      "UserLastModifiedDate": "2023-02-21T18:41:41.466Z",
      "RefreshTokens": []
    },
    "clerkofcourt@example.com": {
      "Username": "clerkofcourt@example.com",
      "Password": "Testing1234$",
      "Attributes": [
        {
          "Name": "sub",
          "Value": "23dd8806-c0c7-4265-81f0-5f264ef78248"
        },
        {
          "Name": "custom:userId",
          "Value": "23dd8806-c0c7-4265-81f0-5f264ef78248"
        },
        {
          "Name": "email",
          "Value": "clerkofcourt@example.com"
        },
        {
          "Name": "email_verified",
          "Value": "True"
        },
        {
          "Name": "custom:role",
          "Value": "clerkofcourt"
        },
        {
          "Name": "custom:name",
          "Value": "Test Clerk of Court"
        }
      ],
      "Enabled": false,
      "UserStatus": "CONFIRMED",
      "UserCreateDate": "2023-01-24T23:54:42.392Z",
      "UserLastModifiedDate": "2023-02-21T18:41:41.466Z",
      "RefreshTokens": []
    },
    "trialclerk@example.com": {
      "Username": "trialclerk@example.com",
      "Password": "Testing1234$",
      "Attributes": [
        {
          "Name": "sub",
          "Value": "f0a1e52a-876f-4c03-853c-f66e407e5a1e"
        },
        {
          "Name": "custom:userId",
          "Value": "f0a1e52a-876f-4c03-853c-f66e407e5a1e"
        },
        {
          "Name": "email",
          "Value": "trialclerk@example.com"
        },
        {
          "Name": "email_verified",
          "Value": "True"
        },
        {
          "Name": "custom:role",
          "Value": "trialclerk"
        },
        {
          "Name": "custom:name",
          "Value": "Test Trial Clerk"
        }
      ],
      "Enabled": false,
      "UserStatus": "CONFIRMED",
      "UserCreateDate": "2023-01-24T23:54:42.392Z",
      "UserLastModifiedDate": "2023-02-21T18:41:41.466Z",
      "RefreshTokens": []
    },
    "trialclerk1@example.com": {
      "Username": "trialclerk1@example.com",
      "Password": "Testing1234$",
      "Attributes": [
        {
          "Name": "sub",
          "Value": "d1f8a729-cbfa-4d22-a09b-73743a12f188"
        },
        {
          "Name": "custom:userId",
          "Value": "d1f8a729-cbfa-4d22-a09b-73743a12f188"
        },
        {
          "Name": "email",
          "Value": "trialclerk1@example.com"
        },
        {
          "Name": "email_verified",
          "Value": "True"
        },
        {
          "Name": "custom:role",
          "Value": "trialclerk"
        },
        {
          "Name": "custom:name",
          "Value": "Test trialclerk1"
        }
      ],
      "Enabled": false,
      "UserStatus": "CONFIRMED",
      "UserCreateDate": "2023-01-24T23:54:42.392Z",
      "UserLastModifiedDate": "2023-02-21T18:41:41.466Z",
      "RefreshTokens": []
    },
    "colvinschambers@example.com": {
      "Username": "colvinschambers@example.com",
      "Password": "Testing1234$",
      "Attributes": [
        {
          "Name": "sub",
          "Value": "9c9292a4-2d5d-45b1-b67f-ac0e1c9b5df5"
        },
        {
          "Name": "custom:userId",
          "Value": "9c9292a4-2d5d-45b1-b67f-ac0e1c9b5df5"
        },
        {
          "Name": "email",
          "Value": "colvinschambers@example.com"
        },
        {
          "Name": "email_verified",
          "Value": "True"
        },
        {
          "Name": "custom:role",
          "Value": "chambers"
        },
        {
          "Name": "custom:name",
          "Value": "Test Colvin's Chambers"
        }
      ],
      "Enabled": false,
      "UserStatus": "CONFIRMED",
      "UserCreateDate": "2023-01-24T23:54:42.392Z",
      "UserLastModifiedDate": "2023-02-21T18:41:41.466Z",
      "RefreshTokens": []
    },
    "ashfordschambers@example.com": {
      "Username": "ashfordschambers@example.com",
      "Password": "Testing1234$",
      "Attributes": [
        {
          "Name": "sub",
          "Value": "817b48c5-d4e5-4544-9e11-9ba0102918f4"
        },
        {
          "Name": "custom:userId",
          "Value": "817b48c5-d4e5-4544-9e11-9ba0102918f4"
        },
        {
          "Name": "email",
          "Value": "ashfordschambers@example.com"
        },
        {
          "Name": "email_verified",
          "Value": "True"
        },
        {
          "Name": "custom:role",
          "Value": "chambers"
        },
        {
          "Name": "custom:name",
          "Value": "Test Ashford's Chambers"
        }
      ],
      "Enabled": false,
      "UserStatus": "CONFIRMED",
      "UserCreateDate": "2023-01-24T23:54:42.392Z",
      "UserLastModifiedDate": "2023-02-21T18:41:41.466Z",
      "RefreshTokens": []
    },
    "buchschambers@example.com": {
      "Username": "buchschambers@example.com",
      "Password": "Testing1234$",
      "Attributes": [
        {
          "Name": "sub",
          "Value": "49421c68-0c09-4b4b-b32c-a535279be8d0"
        },
        {
          "Name": "custom:userId",
          "Value": "49421c68-0c09-4b4b-b32c-a535279be8d0"
        },
        {
          "Name": "email",
          "Value": "buchschambers@example.com"
        },
        {
          "Name": "email_verified",
          "Value": "True"
        },
        {
          "Name": "custom:role",
          "Value": "chambers"
        },
        {
          "Name": "custom:name",
          "Value": "Test Buch's Chambers"
        }
      ],
      "Enabled": false,
      "UserStatus": "CONFIRMED",
      "UserCreateDate": "2023-01-24T23:54:42.392Z",
      "UserLastModifiedDate": "2023-02-21T18:41:41.466Z",
      "RefreshTokens": []
    },
    "carluzzoschambers@example.com": {
      "Username": "carluzzoschambers@example.com",
      "Password": "Testing1234$",
      "Attributes": [
        {
          "Name": "sub",
          "Value": "8c0902ab-d156-4cca-b80d-43f595aa5ab0"
        },
        {
          "Name": "custom:userId",
          "Value": "8c0902ab-d156-4cca-b80d-43f595aa5ab0"
        },
        {
          "Name": "email",
          "Value": "carluzzoschambers@example.com"
        },
        {
          "Name": "email_verified",
          "Value": "True"
        },
        {
          "Name": "custom:role",
          "Value": "chambers"
        },
        {
          "Name": "custom:name",
          "Value": "Test Carluzzo's Chambers"
        }
      ],
      "Enabled": false,
      "UserStatus": "CONFIRMED",
      "UserCreateDate": "2023-01-24T23:54:42.392Z",
      "UserLastModifiedDate": "2023-02-21T18:41:41.466Z",
      "RefreshTokens": []
    },
    "cohenschambers@example.com": {
      "Username": "cohenschambers@example.com",
      "Password": "Testing1234$",
      "Attributes": [
        {
          "Name": "sub",
          "Value": "0bd3bc49-4e46-4caa-adeb-4960c56e17c8"
        },
        {
          "Name": "custom:userId",
          "Value": "0bd3bc49-4e46-4caa-adeb-4960c56e17c8"
        },
        {
          "Name": "email",
          "Value": "cohenschambers@example.com"
        },
        {
          "Name": "email_verified",
          "Value": "True"
        },
        {
          "Name": "custom:role",
          "Value": "chambers"
        },
        {
          "Name": "custom:name",
          "Value": "Test Cohen's Chambers"
        }
      ],
      "Enabled": false,
      "UserStatus": "CONFIRMED",
      "UserCreateDate": "2023-01-24T23:54:42.392Z",
      "UserLastModifiedDate": "2023-02-21T18:41:41.466Z",
      "RefreshTokens": []
    },
    "gustafsonschambers@example.com": {
      "Username": "gustafsonschambers@example.com",
      "Password": "Testing1234$",
      "Attributes": [
        {
          "Name": "sub",
          "Value": "3ce1dad5-87ee-4b00-a4fb-f7f80296a5c2"
        },
        {
          "Name": "custom:userId",
          "Value": "3ce1dad5-87ee-4b00-a4fb-f7f80296a5c2"
        },
        {
          "Name": "email",
          "Value": "gustafsonschambers@example.com"
        },
        {
          "Name": "email_verified",
          "Value": "True"
        },
        {
          "Name": "custom:role",
          "Value": "chambers"
        },
        {
          "Name": "custom:name",
          "Value": "Test Gustafson's Chambers"
        }
      ],
      "Enabled": false,
      "UserStatus": "CONFIRMED",
      "UserCreateDate": "2023-01-24T23:54:42.392Z",
      "UserLastModifiedDate": "2023-02-21T18:41:41.466Z",
      "RefreshTokens": []
    },
    "pughschambers@example.com": {
      "Username": "pughschambers@example.com",
      "Password": "Testing1234$",
      "Attributes": [
        {
          "Name": "sub",
          "Value": "9fbae83a-a55b-4132-96df-e04a8ee675e3"
        },
        {
          "Name": "custom:userId",
          "Value": "9fbae83a-a55b-4132-96df-e04a8ee675e3"
        },
        {
          "Name": "email",
          "Value": "pughschambers@example.com"
        },
        {
          "Name": "email_verified",
          "Value": "True"
        },
        {
          "Name": "custom:role",
          "Value": "chambers"
        },
        {
          "Name": "custom:name",
          "Value": "Test Pugh's Chambers"
        }
      ],
      "Enabled": false,
      "UserStatus": "CONFIRMED",
      "UserCreateDate": "2023-01-24T23:54:42.392Z",
      "UserLastModifiedDate": "2023-02-21T18:41:41.466Z",
      "RefreshTokens": []
    },
    "urdaschambers@example.com": {
      "Username": "urdaschambers@example.com",
      "Password": "Testing1234$",
      "Attributes": [
        {
          "Name": "sub",
          "Value": "44f02385-e4c6-49f9-a554-ecf93531d8a3"
        },
        {
          "Name": "custom:userId",
          "Value": "44f02385-e4c6-49f9-a554-ecf93531d8a3"
        },
        {
          "Name": "email",
          "Value": "urdaschambers@example.com"
        },
        {
          "Name": "email_verified",
          "Value": "True"
        },
        {
          "Name": "custom:role",
          "Value": "chambers"
        },
        {
          "Name": "custom:name",
          "Value": "Test Urda's Chambers"
        }
      ],
      "Enabled": false,
      "UserStatus": "CONFIRMED",
      "UserCreateDate": "2023-01-24T23:54:42.392Z",
      "UserLastModifiedDate": "2023-02-21T18:41:41.466Z",
      "RefreshTokens": []
    },
    "floater@example.com": {
      "Username": "floater@example.com",
      "Password": "Testing1234$",
      "Attributes": [
        {
          "Name": "sub",
          "Value": "9ef02385-e4c6-49f9-a554-ecf93531d8a4"
        },
        {
          "Name": "custom:userId",
          "Value": "9ef02385-e4c6-49f9-a554-ecf93531d8a4"
        },
        {
          "Name": "email",
          "Value": "floater@example.com"
        },
        {
          "Name": "email_verified",
          "Value": "True"
        },
        {
          "Name": "custom:role",
          "Value": "floater"
        },
        {
          "Name": "custom:name",
          "Value": "Test Floater"
        }
      ],
      "Enabled": false,
      "UserStatus": "CONFIRMED",
      "UserCreateDate": "2023-01-24T23:54:42.392Z",
      "UserLastModifiedDate": "2023-02-21T18:41:41.466Z",
      "RefreshTokens": []
    },
    "floater1@example.com": {
      "Username": "floater1@example.com",
      "Password": "Testing1234$",
      "Attributes": [
        {
          "Name": "sub",
          "Value": "5dffc4d8-423d-4de9-bca0-585c7b6627f7"
        },
        {
          "Name": "custom:userId",
          "Value": "5dffc4d8-423d-4de9-bca0-585c7b6627f7"
        },
        {
          "Name": "email",
          "Value": "floater1@example.com"
        },
        {
          "Name": "email_verified",
          "Value": "True"
        },
        {
          "Name": "custom:role",
          "Value": "floater"
        },
        {
          "Name": "custom:name",
          "Value": "Test Floater1"
        }
      ],
      "Enabled": false,
      "UserStatus": "CONFIRMED",
      "UserCreateDate": "2023-01-24T23:54:42.392Z",
      "UserLastModifiedDate": "2023-02-21T18:41:41.466Z",
      "RefreshTokens": []
    },
    "general@example.com": {
      "Username": "general@example.com",
      "Password": "Testing1234$",
      "Attributes": [
        {
          "Name": "sub",
          "Value": "0a03718f-595e-4e2e-bde0-e0b3c3c5ae16"
        },
        {
          "Name": "custom:userId",
          "Value": "0a03718f-595e-4e2e-bde0-e0b3c3c5ae16"
        },
        {
          "Name": "email",
          "Value": "general@example.com"
        },
        {
          "Name": "email_verified",
          "Value": "True"
        },
        {
          "Name": "custom:role",
          "Value": "general"
        },
        {
          "Name": "custom:name",
          "Value": "Test General"
        }
      ],
      "Enabled": false,
      "UserStatus": "CONFIRMED",
      "UserCreateDate": "2023-01-24T23:54:42.392Z",
      "UserLastModifiedDate": "2023-02-21T18:41:41.466Z",
      "RefreshTokens": []
    },
    "reportersoffice@example.com": {
      "Username": "reportersoffice@example.com",
      "Password": "Testing1234$",
      "Attributes": [
        {
          "Name": "sub",
          "Value": "27fc1b7c-5386-4dd1-bfbe-c2b4ae8d459f"
        },
        {
          "Name": "custom:userId",
          "Value": "27fc1b7c-5386-4dd1-bfbe-c2b4ae8d459f"
        },
        {
          "Name": "email",
          "Value": "reportersoffice@example.com"
        },
        {
          "Name": "email_verified",
          "Value": "True"
        },
        {
          "Name": "custom:role",
          "Value": "reportersOffice"
        },
        {
          "Name": "custom:name",
          "Value": "Test Reporter's Office"
        }
      ],
      "Enabled": false,
      "UserStatus": "CONFIRMED",
      "UserCreateDate": "2023-01-24T23:54:42.392Z",
      "UserLastModifiedDate": "2023-02-21T18:41:41.466Z",
      "RefreshTokens": []
    },
    "inactivepractitioner@example.com": {
      "Username": "inactivepractitioner@example.com",
      "Password": "Testing1234$",
      "Attributes": [
        {
          "Name": "sub",
          "Value": "c0daa0a7-a66b-4eae-949b-9ae0f8a32e46"
        },
        {
          "Name": "custom:userId",
          "Value": "c0daa0a7-a66b-4eae-949b-9ae0f8a32e46"
        },
        {
          "Name": "email",
          "Value": "inactivepractitioner@example.com"
        },
        {
          "Name": "email_verified",
          "Value": "True"
        },
        {
          "Name": "custom:role",
          "Value": "inactivePractitioner"
        },
        {
          "Name": "custom:name",
          "Value": "Test Inactive Practitioner"
        }
      ],
      "Enabled": false,
      "UserStatus": "CONFIRMED",
      "UserCreateDate": "2023-01-24T23:54:42.392Z",
      "UserLastModifiedDate": "2023-02-21T18:41:41.466Z",
      "RefreshTokens": []
    },
    "irssuperuser@example.com": {
      "Username": "irssuperuser@example.com",
      "Password": "Testing1234$",
      "Attributes": [
        {
          "Name": "sub",
          "Value": "02c9b614-e498-4dae-b0f5-751b9ab5e8b3"
        },
        {
          "Name": "custom:userId",
          "Value": "02c9b614-e498-4dae-b0f5-751b9ab5e8b3"
        },
        {
          "Name": "email",
          "Value": "irssuperuser@example.com"
        },
        {
          "Name": "email_verified",
          "Value": "True"
        },
        {
          "Name": "custom:role",
          "Value": "irsSuperuser"
        },
        {
          "Name": "custom:name",
          "Value": "Test IRS Superuser"
        }
      ],
      "Enabled": false,
      "UserStatus": "CONFIRMED",
      "UserCreateDate": "2023-01-24T23:54:42.392Z",
      "UserLastModifiedDate": "2023-02-21T18:41:41.466Z",
      "RefreshTokens": []
    }
  }
}