{
  "Version": "2012-10-17",
  "Statement": [
    {
      "Effect": "Allow",
      "Action": "s3:ListBucket",
      "Resource": "arn:aws:s3:::ustc-case-mgmt.flexion.us.terraform.deploys",
      "Principal": {
        "AWS": "arn:aws:iam::515554424717:user/CircleCI"
      }
    },
    {
      "Effect": "Allow",
      "Action": ["s3:GetObject", "s3:PutObject"],
      "Resource": "arn:aws:s3:::ustc-case-mgmt.flexion.us.terraform.deploys/ui-exp.tfstate",
      "Principal": {
        "AWS": "arn:aws:iam::515554424717:user/CircleCI"
      }
    }
  ]
}
